{
  "slug": "parking-ac-ghana-kumasi-industrial-zone",
  "title": "Parking Air Conditioning for Kumasi Industrial Zone: Powering Ghana's Manufacturing Logistics",
  "date": "2026-03-31",
  "category": "Fleet Applications",
  "image": "/images/blog/kumasi-industrial.jpg",
  "imageAlt": "Industrial logistics vehicles in Kumasi equipped with CoolDrivePro parking AC systems",
  "metaDescription": "Optimize industrial logistics in Kumasi with CoolDrivePro parking air conditioning. DC-powered cooling solutions for Ghana's manufacturing heartland and growing industrial sector.",
  "content": [
    {
      "heading": "Introduction: Ghana's Industrial Heartland",
      "body": "Kumasi, the historic capital of the Ashanti Kingdom and Ghana's second-largest city, has emerged as the industrial powerhouse of West Africa's second-largest economy and a critical node in regional manufacturing and trade networks. With a metropolitan population exceeding 3.5 million residents and strategic location at the intersection of major transport corridors connecting Ghana's coastal ports to the Sahel region and landlocked neighbors, Kumasi serves as the commercial and manufacturing hub for the country's central and northern territories, handling goods and materials that sustain economic activity across millions of square kilometers. The city's industrial landscape encompasses diverse sectors including automotive assembly and parts manufacturing, food processing and agribusiness, wood and furniture production, textiles and garments, pharmaceuticals, chemicals, construction materials, and an expanding base of services and technology enterprises that contribute to Ghana's economic diversification and growth. The Greater Kumasi Industrial Zone, including the planned Boankra Inland Port and Free Zone enclave, represents one of West Africa's most significant industrial development projects, designed to transform the region into an export-oriented manufacturing hub serving both regional markets and international buyers seeking African production sources. This industrial expansion creates substantial demand for reliable logistics services, with commercial vehicle fleets operating under challenging conditions that include tropical heat, high humidity, extended loading and unloading times, complex multi-stop distribution patterns, and infrastructure that, while improving, still presents operational challenges compared to developed country standards. For the logistics providers who serve Kumasi's manufacturing sector, vehicle downtime, driver fatigue, cargo damage, and operational inefficiencies represent significant costs that directly impact competitiveness in an increasingly demanding market where manufacturers expect just-in-time delivery, perfect order fulfillment, and cost efficiency that matches global standards. CoolDrivePro's parking air conditioning systems are transforming industrial logistics operations across Kumasi and the Ashanti Region, providing reliable climate control that enhances driver productivity, protects cargo integrity, reduces operational costs, and enables logistics providers to meet the demanding requirements of modern manufacturing supply chains. This comprehensive analysis examines the unique characteristics of Kumasi's industrial logistics sector, explores the specific challenges facing operators in this dynamic environment, and demonstrates how advanced parking AC technology is supporting Ghana's manufacturing transformation and economic development objectives."
    },
    {
      "heading": "Kumasi's Manufacturing and Logistics Ecosystem",
      "body": "The Ashanti Region's industrial economy has evolved substantially from its historical foundations in cocoa, gold, and timber to encompass a diversified manufacturing base that positions Kumasi as Ghana's premier industrial city and an emerging center for West African production. The Suame Magazine, one of Africa's largest informal industrial zones, houses thousands of artisanal workshops and small enterprises producing automotive parts, machinery components, metal goods, and engineering services that supply markets across West Africa and demonstrate the region's industrial ingenuity and entrepreneurial spirit. Formal industrial areas including the Kaase Industrial Enclave and Asokwa Industrial Area host multinational manufacturing operations, Ghanaian industrial champions, and foreign direct investment projects across sectors including beverages, pharmaceuticals, plastics, and consumer goods. The planned Greater Kumasi Industrial City at Boankra will add over 5,000 acres of serviced industrial land for export-oriented manufacturing, including processing of agricultural products, assembly operations, and logistics facilities that will reshape the region's economic geography and create new requirements for efficient transport services. This industrial ecosystem creates complex logistics requirements spanning inbound raw materials and components from domestic and international sources, inter-factory transfers between processing stages, finished goods distribution to domestic markets and export facilities, and reverse logistics for returns and recycling that complete the circular economy. The Suame Magazine automotive cluster alone generates substantial logistics demand, with parts and components moving between workshops, suppliers, and customers throughout Ghana and neighboring countries in a dynamic ecosystem of manufacturing and commerce. Food processing operations, including cocoa processing for chocolate manufacturing, fruit juice production, poultry processing, and traditional food products, require temperature-sensitive logistics that can be compromised by extreme heat during transport if adequate climate control is not maintained. The planned Boankra Inland Port, connecting to the Port of Tema via rail and road, will add significant container traffic to Kumasi's logistics landscape, with trucks spending extended periods at the facility during customs clearance, cargo handling, and documentation processing that demands reliable vehicle systems and comfortable conditions for drivers. Each segment of this diverse industrial economy relies on commercial vehicle fleets that operate under tropical conditions creating significant climate control challenges that affect both human welfare and cargo integrity."
    },
    {
      "heading": "Climate Challenges in Ghana's Interior",
      "body": "Kumasi's location in Ghana's forest zone, approximately 300 meters above sea level and 200 kilometers from the Atlantic coast, creates climatic conditions that present distinct challenges for industrial logistics operations different from both coastal environments and the drier savanna regions to the north. The city experiences a tropical wet and dry climate with consistently high temperatures throughout the year, averaging 26-32°C (79-90°F) with limited seasonal variation that means heat management is a year-round concern rather than a seasonal challenge. Unlike coastal areas where maritime breezes provide some relief, Kumasi's inland location results in stagnant, humid conditions that can feel oppressive, particularly during the wet season when humidity levels regularly exceed 80% and the combination of heat and moisture creates heat index values that stress human thermoregulation systems. The two rainy seasons—major rains from April to June and minor rains from September to November—create additional operational challenges including flooded roads in low-lying areas, muddy loading areas at industrial facilities that lack paved surfaces, reduced visibility during heavy downpours, and the need to maintain climate control in enclosed vehicles during precipitation when windows must remain closed. The Harmattan winds that blow from the Sahara during December through February bring fine dust that infiltrates vehicle systems, reduces air quality, creates respiratory challenges for drivers, and deposits abrasive particles that accelerate wear on mechanical components and air conditioning systems. For commercial vehicles serving industrial operations, these conditions create a challenging operating environment: drivers must remain alert and focused during complex loading procedures, documentation requirements, and navigation of industrial estates while combating heat stress that impairs cognitive function and physical performance precisely when attention to detail is most critical; cargo—including temperature-sensitive industrial inputs and outputs, perishable food products, and moisture-sensitive materials—faces quality risks from extreme temperatures and humidity variations; and vehicle systems experience accelerated wear from dust, humidity, and constant high-load operation that increases maintenance costs and reduces vehicle availability."
    },
    {
      "heading": "Industrial Logistics: Unique Operational Requirements",
      "body": "Industrial logistics operations in Kumasi face requirements distinct from general freight or passenger transport that make parking air conditioning particularly valuable and in many cases essential for meeting customer expectations and operational efficiency targets. Extended dwell times at manufacturing facilities are common, as loading and unloading procedures for industrial cargo often involve specialized equipment such as forklifts and cranes, quality inspections to verify quantities and condition, documentation requirements including waybills and delivery notes, and security procedures that can keep vehicles stationary for hours while remaining ready for immediate departure when loading is complete. Just-in-time delivery schedules, increasingly common among multinational manufacturers and larger Ghanaian enterprises seeking to minimize inventory costs, require drivers to arrive within precise time windows and wait if early, creating situations where vehicles must remain parked with climate control for extended periods without knowing exactly when loading or unloading will commence. Multi-stop distribution patterns serving industrial estates involve frequent engine cycling that accelerates wear and increases fuel consumption if conventional AC is used at each stop, while the cumulative effect of multiple short stops with idling can consume substantial fuel without contributing to distance traveled. Driver waiting periods between assignments, common in industrial logistics where demand fluctuates with production schedules, seasonal variations, and order patterns, create situations where vehicles must maintain comfortable conditions without engine operation to ensure driver availability and prevent the health risks of heat exposure during idle periods. Cargo protection requirements for industrial inputs—including chemicals that may be temperature-sensitive, precision components that can be damaged by heat or moisture, and raw materials with specific storage requirements—extend to transport conditions, with extreme cabin temperatures potentially compromising product quality even for goods not formally classified as requiring refrigeration. For logistics providers operating on thin margins in a competitive market where manufacturers constantly pressure transport costs, these operational characteristics make fuel efficiency and driver productivity critical success factors that parking air conditioning directly addresses by eliminating engine idling while maintaining comfort and cargo protection."
    },
    {
      "heading": "CoolDrivePro Solutions for Industrial Applications",
      "body": "CoolDrivePro has developed specialized parking air conditioning systems specifically optimized for the demanding requirements of industrial logistics operations in Kumasi and similar manufacturing hubs, incorporating features that address the unique challenges of high-heat environments, dusty conditions, extended stationary periods, and the reliability requirements of just-in-time supply chains. The CDP-Industrial series offers robust cooling solutions with 2,500-4,000 BTU capacity designed for heavy-duty commercial vehicles serving manufacturing and distribution operations, with components selected for durability and reliability in challenging environments where system failure can disrupt customer operations and damage business relationships. These systems feature industrial-grade components engineered for reliability in high-dust environments, with enhanced multi-stage filtration that protects internal components from the particulate contamination common in industrial zones, construction areas, and unpaved roads that characterize much of Kumasi's logistics landscape. The CDP-Fleet variant provides optimized solutions for delivery vans and light commercial vehicles serving distribution operations, offering compact installation with 1,800-2,500 BTU capacity sufficient for frequent-stop urban and industrial operations where vehicles need quick recovery capability between stops. All industrial-focused systems feature rapid cool-down capability that quickly restores comfortable temperatures after loading activities require door openings that admit hot air, intelligent battery management that ensures starting capability even after extended stationary periods and prevents the disruptions that would occur if vehicles failed to start when loading is complete, and durable construction that withstands the vibration, dust, and stress of industrial vehicle operations in challenging African conditions. Installation options accommodate the diverse vehicle types common in Kumasi's industrial fleet, from Mercedes Actros, MAN, and Scania trucks serving long-haul routes to Isuzu, Fuso, and Dongfeng distribution vehicles navigating industrial estates, urban delivery areas, and rural roads connecting to farming communities. CoolDrivePro's Ghana technical team provides comprehensive support for industrial fleet operators including site assessment to understand specific operational requirements, professional installation by certified technicians, driver training programs that ensure optimal system usage, and preventive maintenance programs designed to maximize system availability and operational benefits throughout the vehicle lifecycle."
    },
    {
      "heading": "Economic Benefits for Ghanaian Industrial Logistics",
      "body": "For logistics providers serving Kumasi's industrial sector, parking air conditioning investments deliver compelling economic returns that justify implementation in Ghana's cost-competitive market environment where every operational advantage contributes to business survival and growth. Fuel savings from elimination of engine idling are particularly significant given the extended dwell times and frequent stops typical of industrial logistics operations—vehicles may spend 25-40% of operating hours stationary during loading, unloading, waiting, and documentation processing that are unavoidable in current supply chain structures. At Ghanaian fuel prices, savings of 50-100 Ghana Cedis daily are typical for industrial logistics vehicles depending on utilization and route characteristics, achieving payback periods of 10-15 months for most installations—attractive returns that improve as fuel prices increase and congestion worsens around industrial areas. Reduced engine operating hours extend maintenance intervals and prolong vehicle lifespan, critical considerations for logistics providers managing significant vehicle fleets in a market where replacement costs continue rising due to currency fluctuations, import duties, and financing costs that make vehicle preservation an important economic strategy. Driver retention improvements deliver substantial indirect savings, as experienced industrial drivers familiar with facility procedures, cargo handling requirements, route optimization, and customer expectations command premium wages and are difficult to replace in a labor market where qualified commercial drivers have increasing employment options across Ghana's growing economy. Cargo protection benefits include reduced damage claims for temperature-sensitive industrial inputs and outputs, supporting quality assurance requirements of multinational manufacturing clients who may impose penalties for damaged deliveries or terminate relationships with unreliable logistics providers. Operational efficiency improvements from drivers who remain comfortable and alert throughout their shifts translate to faster turnaround times at facilities, fewer errors in complex logistics procedures, improved customer service, and ability to complete more deliveries per day that increases revenue without increasing fleet size. These cumulative benefits enhance competitiveness for logistics providers serving Kumasi's growing industrial base while supporting the broader economic development objectives of Ghana's manufacturing transformation by enabling efficient, reliable supply chains that reduce production costs and improve export competitiveness."
    },
    {
      "heading": "Supporting Ghana's Industrial Transformation",
      "body": "The adoption of parking air conditioning technology across Kumasi's industrial logistics fleet supports Ghana's broader economic transformation objectives and the evolution toward higher-value manufacturing and export-oriented production that is central to the country's development vision. The government's Industrial Transformation Agenda, the African Continental Free Trade Area implementation, and various investment promotion initiatives create frameworks for manufacturing expansion that will substantially increase logistics demand across the Ashanti Region and require more sophisticated supply chain capabilities than currently exist. Logistics efficiency is a critical enabler of manufacturing competitiveness, with transport costs, reliability, and service quality directly impacting production economics, inventory requirements, and export viability that determine whether Ghanaian manufacturers can compete with imports and access regional and global markets. Parking air conditioning contributes to logistics efficiency by reducing fuel costs that directly affect transport pricing, improving driver retention that ensures service consistency, protecting cargo quality that reduces waste and customer complaints, and enabling more intensive vehicle utilization that spreads fixed costs across more deliveries. The technology also supports environmental objectives aligned with Ghana's climate commitments and the sustainability requirements increasingly imposed by international manufacturing clients and export markets where environmental credentials influence purchasing decisions and market access. Each parking AC-equipped vehicle eliminates approximately 2-4 tons of annual CO2 emissions compared to idling-dependent cooling approaches, contributing to the green manufacturing credentials that increasingly influence international purchasing decisions and corporate procurement policies. As Kumasi develops into a major industrial hub serving regional and global markets, and as Ghana advances its position within the African Continental Free Trade Area, the logistics providers who invest in modern, efficient technologies will capture disproportionate market share among manufacturing clients seeking reliable, sustainable supply chain partners capable of supporting their growth and meeting their standards for service quality and environmental responsibility."
    },
    {
      "heading": "Implementation Strategy for Industrial Fleet Operators",
      "body": "Successful parking AC deployment in Kumasi's industrial logistics sector requires implementation strategies adapted to the specific requirements of manufacturing supply chain operations, the characteristics of industrial estates and facilities, and the seasonal patterns that shape commercial activity in Ghana's manufacturing sector. Fleet assessment should begin with analysis of facility service patterns, identifying vehicles with highest utilization, longest dwell times at manufacturing sites, and most challenging route characteristics that generate maximum benefit from parking AC capability and justify priority implementation. Electrical system evaluation is essential, as industrial logistics vehicles often require robust battery systems capable of supporting extended parking AC operation during loading and waiting periods without compromising starting capability or requiring frequent jump-starts that disrupt operations and damage professional relationships with customers. CoolDrivePro's technical team recommends minimum 100Ah battery capacity for typical industrial operations, with 120-150Ah preferred for vehicles serving facilities with extended processing times, operating multiple daily shifts to maximize asset utilization, or working in the hottest periods when cooling demands are highest. Solar integration offers particular value in Ghana's abundant sunshine, with roof-mounted panels providing supplementary charging that extends parking AC runtime and reduces battery stress—ideal for vehicles that spend daylight hours at industrial facilities, in transit between locations, or parked during driver rest periods. Installation timing should consider production schedules at key client facilities, with implementation during lower-volume periods allowing system optimization before peak manufacturing seasons when logistics demand is highest and any performance issues would be most disruptive to customer relationships and revenue. Driver training programs emphasize efficient system operation during industrial procedures, coordination with facility staff regarding loading schedules and parking locations, and battery management practices that ensure reliability throughout demanding workdays. Maintenance protocols address the dust and humidity challenges of Ghana's interior environment, with preventive service schedules designed to ensure maximum availability during critical manufacturing periods when just-in-time deliveries are essential and delays can shut down production lines. CoolDrivePro's Ghana service network provides comprehensive support including site assessment, professional installation, preventive maintenance programs, and emergency repair services to ensure logistics providers can meet their manufacturing clients' demanding service requirements and contribute to Ghana's industrial transformation."
    },
    {
      "heading": "The Future of Industrial Logistics in Ghana",
      "body": "Kumasi's industrial logistics sector stands at an important juncture where technological adoption, infrastructure development, and changing customer expectations are creating both opportunities and imperatives for modernization that will shape the industry's evolution over coming decades. The planned Boankra Inland Port will transform logistics patterns in the region, creating a major multimodal facility that will require efficient truck operations to interface with rail services and container handling equipment while meeting the service standards of international shipping lines and corporate clients. E-commerce growth is extending into industrial supply chains, with manufacturers and distributors expecting the same real-time tracking, predictable delivery windows, and service reliability that consumers have come to expect from online retail. Regional integration under the African Continental Free Trade Area will create new cross-border logistics requirements, with Kumasi-positioned operators able to serve markets in Burkina Faso, Mali, and Cote d'Ivoire that are currently underserved by efficient logistics services. Parking air conditioning technology supports these future developments by enabling the reliable, efficient, professional truck operations that will be required to compete in increasingly sophisticated markets and meet the standards of international manufacturing clients. As Ghana's economy continues to grow and diversify, and as Kumasi consolidates its position as West Africa's premier inland industrial hub, the logistics providers who invest in modern technology, professional operations, and worker welfare today will capture disproportionate market share and influence the sector's evolution toward world-class standards that serve the country's development objectives."
    },
    {
      "heading": "Conclusion: Enabling Ghana's Manufacturing Future",
      "body": "Kumasi's evolution from the historic capital of the Ashanti Kingdom to the emerging industrial heartland of West Africa represents one of the continent's most significant economic transformation stories, demonstrating Ghana's potential to become a manufacturing powerhouse serving regional and global markets with quality products produced by skilled workers using efficient supply chains. The manufacturing and logistics sectors that drive this transformation operate under challenging tropical conditions that demand innovative technological solutions to maintain competitiveness with imports and production sources from other regions with more favorable climates or better infrastructure. CoolDrivePro's parking air conditioning systems provide industrial logistics operators with the tools they need to meet these challenges, delivering reliable climate control that enhances driver productivity, protects cargo integrity, reduces operational costs, supports environmental sustainability objectives, and enables logistics providers to meet the demanding requirements of modern manufacturing supply chains that operate on thin margins and cannot tolerate disruptions or quality failures. For the logistics providers who serve Kumasi's diverse manufacturing base—from the artisanal workshops of Suame Magazine that demonstrate African industrial ingenuity to the multinational operations of the industrial enclaves and the emerging enterprises of the Greater Kumasi Industrial City—parking AC investment delivers measurable returns that justify implementation in a competitive market while supporting Ghana's broader industrial transformation by enabling more efficient logistics operations that reduce manufacturing costs and enhance export competitiveness. The technology also contributes to worker welfare in an industry where drivers often face difficult conditions, supporting Ghana's development objectives for decent work and economic growth that benefit all participants in the industrial economy. As the Ashanti Region continues its development as a major industrial hub and as Ghana advances its position within the African Continental Free Trade Area and global economy, the logistics operators who invest in modern, efficient technologies today will build the capabilities and market positions that drive long-term success and contribute to the prosperity of the communities they serve. CoolDrivePro remains committed to supporting Ghana's manufacturing transformation through continued innovation, comprehensive technical support, and partnerships with logistics providers working to build world-class supply chain capabilities for West Africa's industrial future."
    }
  ]
}
